angou_huobi/__init__.py
angou_huobi/auth_utils.py
angou_huobi/rest.py
angou_huobi-3.dist-info/LICENSE.txt
angou_huobi-3.dist-info/METADATA
angou_huobi-3.dist-info/RECORD
angou_huobi-3.dist-info/WHEEL
angou_huobi-3.dist-info/top_level.txt
