Metadata-Version: 2.1
Name: angou-huobi
Version: 3
Summary: Lightweight and suckless Huobi REST API client library
Home-page: http://github.com/angou-exchange-utils/angou-huobi
Author: shdown
Author-email: shdownnine@gmail.com
License: LGPLv3
Download-URL: https://github.com/angou-exchange-utils/angou-huobi/tarball/v3
Keywords: angou huobi crypto exchange
Platform: any
Classifier: Development Status :: 1 - Planning
Classifier: License :: OSI Approved :: GNU Lesser General Public License v3 (LGPLv3)
Classifier: Programming Language :: Python :: 3 :: Only
Classifier: Topic :: Internet
Classifier: Topic :: Software Development :: Libraries
Requires-Python: >=3
Requires-Dist: requests
